{
	"core:rampart" :
	{
		"town" :
		{
			"structures" :
			{
			"dwellingLvl4B": { "animation" : "town-screen/rampart/DWRMT4ALT.def", "x" : 285, "y" : 52, "z" : 1, "border" : "town-screen/rampart/buildings-border/TONalt1.bmp", "area" : "town-screen/rampart/buildings-area/TZNalt1.bmp" }, 
			"dwellingUpLvl4B": { "animation" : "town-screen/rampart/DWRMT4UPALT", "x" : 285, "y" : 52, "z" : 1, "border" : "town-screen/rampart/buildings-border/TONaup1.bmp", "area" : "town-screen/rampart/buildings-area/TZNaup1.bmp" } 
			},
			"buildingsIcons": "town-screen/rampart/ALTHALLRMT.DEF",
			"hallBackground": "town-screen/rampart/rampartHallBg.BMP",
			"hallSlots":
			[
				[ [ "villageHall", "townHall", "cityHall", "capitol" ], [ "fort", "citadel", "castle" ], [ "tavern" ], [ "blacksmith" ] ],
				[ [ "marketplace", "resourceSilo" ], [ "mageGuild1", "mageGuild2", "mageGuild3", "mageGuild4", "mageGuild5" ], [ "special1", "special2" ] ],
				[ [ "special3" ], [ "horde2", "horde2Upgr" ], [ "horde1", "horde1Upgr" ], [ "dwellingLvl4B", "dwellingUpLvl4B" ] ],
				[ [ "dwellingLvl1", "dwellingUpLvl1" ], [ "dwellingLvl2", "dwellingUpLvl2" ], [ "dwellingLvl3", "dwellingUpLvl3" ], [ "dwellingLvl4", "dwellingUpLvl4" ] ],
				[ [ "dwellingLvl5", "dwellingUpLvl5" ], [ "dwellingLvl6", "dwellingUpLvl6" ], [ "dwellingLvl7", "dwellingUpLvl7" ] ]
			],
			"creatures" :
			[
				["centaur", "centaurCaptain"],
				["dwarf", "battleDwarf"],
				["woodElf", "grandElf"],
				["pegasus", "silverPegasus", "mdtDryad", "mdtOakDryad" ],
				["dendroidGuard", "dendroidSoldier"],
				["unicorn", "warUnicorn"],
				["greenDragon", "goldDragon"]
			],
			
			"buildings" :
			{
			"dwellingLvl4":   
				{ 
				"requires" : [ "allOf", [ "dwellingLvl3" ], [ "noneOf", [ "dwellingLvl4B" ] ] ]
				},
			
			"dwellingLvl4B" :
				{
					"description" : "The Treehouse allows you to recruit Dryads.",
					"name" : "Treehouse",
					"cost" : 
					{
						"gold" : 2000,
						"wood" : 10,
						"crystal" : 5
					},
					"requires" : [ "allOf", ["dwellingLvl2"], [ "mageGuild1" ], [ "noneOf", [ "dwellingLvl4" ] ] ],
					"id" : 47
				},
			"dwellingUpLvl4B" :
				{
					"description" : "The Treehouse allows you to recruit Oak Dryads.",
					"name" : "Upg. Treehouse",
					"id" : 54,
					"cost" : 
					{
						"wood" : 5,
						"gold" : 2000
					},
					"upgrades" : "dwellingLvl4B"
				},
			"dwellingLvl6":   
				{ 
					"requires" : 
					[ 
						"allOf", 
						[ "dwellingLvl3" ], 
						[
							"anyOf", 
								[ "dwellingLvl4" ], 
								[ "dwellingLvl4B" ]	
						]
					]	
				}
			}	
		}
	}	
}
